pyreto/__init__.py
pyreto/bootstrap.py
pyreto/mc.py
pyreto/vine.py
pyreto/distributions/__init__.py
pyreto/distributions/alpha_stable.py
pyreto/distributions/gpd.py
pyreto/distributions/nig.py
pyreto/distributions/student_t.py
pyreto/distributions/util.py
pyreto-1.0.1.dist-info/METADATA
pyreto-1.0.1.dist-info/WHEEL
pyreto-1.0.1.dist-info/top_level.txt
pyreto-1.0.1.dist-info/RECORD
