Metadata-Version: 2.4
Name: pyreto
Version: 1.0.1
Summary: Tail risk management library with Monte Carlo simulation (classless functional API)
Author-email: AWP <andrewpomorski@proton.me>
License: MIT
Project-URL: Repository, https://gitcode.com/andyski/pyreto-core
Requires-Python: >=3.8
Requires-Dist: numpy>=1.20.0
Requires-Dist: scipy>=1.10.0
Requires-Dist: polars>=0.19.0
Provides-Extra: dev
Requires-Dist: pytest>=6.0; extra == "dev"
